pubkeeper/protocol/legacy/__init__.py
pubkeeper/protocol/legacy/packet.py
pubkeeper/protocol/legacy/protocol.py
pubkeeper.protocol.legacy-1.0.0.dist-info/DESCRIPTION.rst
pubkeeper.protocol.legacy-1.0.0.dist-info/METADATA
pubkeeper.protocol.legacy-1.0.0.dist-info/RECORD
pubkeeper.protocol.legacy-1.0.0.dist-info/WHEEL
pubkeeper.protocol.legacy-1.0.0.dist-info/metadata.json
pubkeeper.protocol.legacy-1.0.0.dist-info/top_level.txt
