Metadata-Version: 2.0
Name: pubkeeper.protocol.legacy
Version: 1.0.0
Summary: Brew, Fill, Consume
Home-page: http://github.com/pubkeeper/python-protocol-legacy
Author: n.io
Author-email: info@n.io
License: UNKNOWN
Keywords: pubkeeper,python-protocol-legacy
Platform: UNKNOWN
Classifier: License :: Other/Proprietary License
Classifier: Programming Language :: Python :: 3
Classifier: Programming Language :: Python :: 3.5
